deel/lip/VERSION
deel/lip/__init__.py
deel/lip/activations.py
deel/lip/callbacks.py
deel/lip/compute_layer_sv.py
deel/lip/constraints.py
deel/lip/initializers.py
deel/lip/losses.py
deel/lip/metrics.py
deel/lip/model.py
deel/lip/normalizers.py
deel/lip/regularizers.py
deel/lip/utils.py
deel/lip/layers/__init__.py
deel/lip/layers/activations.py
deel/lip/layers/base_layer.py
deel/lip/layers/convolutional.py
deel/lip/layers/dense.py
deel/lip/layers/pooling.py
deel/lip/layers/unconstrained.py
deel_lip-1.5.0.dist-info/LICENSE
deel_lip-1.5.0.dist-info/METADATA
deel_lip-1.5.0.dist-info/WHEEL
deel_lip-1.5.0.dist-info/top_level.txt
deel_lip-1.5.0.dist-info/RECORD
