Metadata-Version: 2.1
Name: deel-lip
Version: 1.5.0
Summary: TensorFlow 2 implementation for k-Lipschitz layers
Home-page: https://github.com/deel-ai/deel-lip
Author: Mathieu SERRURIER, Franck MAMALET, Thibaut BOISSIN
Author-email: mathieu.serrurier@irt-saintexupery.com, franck.mamalet@irt-saintexupery.com, thibaut.boissin@irt-saintexupery.com
License: MIT
Classifier: Programming Language :: Python :: 3
Classifier: Programming Language :: Python :: 3.7
Classifier: Programming Language :: Python :: 3.8
Classifier: Programming Language :: Python :: 3.9
Classifier: Programming Language :: Python :: 3.10
Classifier: License :: OSI Approved :: MIT License
Classifier: Operating System :: OS Independent
Requires-Python: >=3.7
License-File: LICENSE
Requires-Dist: numpy
Requires-Dist: tensorflow ~=2.2
Provides-Extra: dev
Requires-Dist: tox ; extra == 'dev'
Requires-Dist: black ; extra == 'dev'
Requires-Dist: flake8 ; extra == 'dev'
Requires-Dist: flake8-black ; extra == 'dev'
Requires-Dist: numpy ; extra == 'dev'
Provides-Extra: docs
Requires-Dist: mkdocs ; extra == 'docs'
Requires-Dist: mkdocs-material ; extra == 'docs'
Requires-Dist: mkdocstrings ; extra == 'docs'
Requires-Dist: mkdocstrings-python ; extra == 'docs'
Requires-Dist: mknotebooks ; extra == 'docs'
Requires-Dist: ipython ; extra == 'docs'
Requires-Dist: black ; extra == 'docs'
